Metadata-Version: 2.1
Name: flythings
Version: 1.4.10
Summary: A python library to add ans search observations into flythings
Home-page: https://github.com/flythings/python
Author: flythings
Author-email: tic@itg.es
License: GPL-3.0
Download-URL: https://github.com/flythings/python/1.4.10.tar.gz
Keywords: flythings,IoT
Platform: UNKNOWN
